ibmdb_tests.py
ibm_db.cpython-314-darwin.so
ibm_db_ctx.py
testfunctions.py
ibm_db_dbi.py
ibm_db_tests/test_alltypes.py
ibm_db_tests/test_111_FieldNumAddCol.py
ibm_db_tests/test_122_FieldNameDiffCaseColNames.py
ibm_db_tests/test_065_FilterTableName.py
ibm_db_tests/test_045_FetchTupleBinaryData_01.py
ibm_db_tests/test_158_FetchAssocNestedSelects_02.py
ibm_db_tests/test_251_FreeResult_02.py
ibm_db_tests/test_221_100PersistentConns.py
ibm_db_tests/test_200_MultipleRsltsetsUniformColDefs.py
ibm_db_tests/test_bool_callproc.py
ibm_db_tests/test_042_FetchTupleMany_02.py
ibm_db_tests/test_020_RollbackDelete.py
ibm_db_tests/test_123_FieldNamePos_01.py
ibm_db_tests/test_197_StatisticsIndexes.py
ibm_db_tests/test_002_ConnDbUncatalogedConn.py
ibm_db_tests/test_232_FieldTypePosName.py
ibm_db_tests/test_InsertRetrieveDateTimeTypeColumn.py
ibm_db_tests/test_015_InsertDeleteRowCount_01.py
ibm_db_tests/test_041_FetchTupleMany_01.py
ibm_db_tests/test_047_FetchTupleMany_06.py
ibm_db_tests/test_140_BindParamSelectStmt.py
ibm_db_tests/test_160_FetchBoth.py
ibm_db_tests/test_312_FetchOne.py
ibm_db_tests/test_050_AutocommitStatus.py
ibm_db_tests/test_004_ConnWrongUserPwd.py
ibm_db_tests/test_114_NumericTest_01.py
ibm_db_tests/test_070_Close.py
ibm_db_tests/test_024_ForeignKeys.py
ibm_db_tests/test_031_ResultIndexPosition.py
ibm_db_tests/test_147_PrepareWithWrongType.py
ibm_db_tests/test_051_SetAutocommit_01.py
ibm_db_tests/test_019_selectRowcountPrefetchPrepOpt.py
ibm_db_tests/test_sp_return.py
ibm_db_tests/test_318_get_sqlcode_DBI.py
ibm_db_tests/test_recreateDB.py
ibm_db_tests/test_054_CursorType.py
ibm_db_tests/test_161_FetchBothNestedSelects_01.py
ibm_db_tests/test_310_ClientInfo.py
ibm_db_tests/test_003_NumAffectedRows.py
ibm_db_tests/test_err_executemany.py
ibm_db_tests/test_265_NoAffectedRows.py
ibm_db_tests/test_066_TableObjects.py
ibm_db_tests/test_264_InsertRetrieveBIGINTTypeColumn.py
ibm_db_tests/test_113_DateTest.py
ibm_db-3.2.8.dist-info/RECORD
ibm_db-3.2.8.dist-info/WHEEL
ibm_db-3.2.8.dist-info/top_level.txt
ibm_db-3.2.8.dist-info/METADATA
ibm_db-3.2.8.dist-info/licenses/LICENSE
