Metadata-Version: 2.1
Name: ibm_db
Version: 3.2.8
Summary: Python DBI driver for DB2 (LUW, zOS, i5)
Home-page: http://pypi.python.org/pypi/ibm_db/
Download-URL: http://code.google.com/p/ibm-db/downloads/list
Author: IBM Application Development Team
Author-email: earamma.kanasavi@ibm.com
License: Apache License 2.0
Keywords: database DB-API interface IBM Data Servers Db2
Platform: Linux32/64
Platform: Win32/64
Platform: MacOS64
Platform: MacARM64
Platform: aix32/64
Platform: ppc32/64
Platform: sunamd32/64
Platform: sun32/64
Platform: ppc64le
Platform: z/OS
Classifier: Development Status :: 5 - Production/Stable
Classifier: Intended Audience :: Developers
Classifier: License :: OSI Approved :: Apache Software License
Classifier: Operating System :: Microsoft :: Windows :: Windows 10
Classifier: Operating System :: Microsoft :: Windows :: Windows 11
Classifier: Operating System :: Unix
Classifier: Operating System :: POSIX :: AIX
Classifier: Operating System :: POSIX :: Linux
Classifier: Operating System :: MacOS
Classifier: Operating System :: MacOS :: MacOS X
Classifier: Programming Language :: Python
Classifier: Programming Language :: Python :: 3.9
Classifier: Programming Language :: Python :: 3.10
Classifier: Programming Language :: Python :: 3.11
Classifier: Programming Language :: Python :: 3.12
Classifier: Programming Language :: Python :: 3.13
Classifier: Programming Language :: Python :: 3.14
Classifier: Topic :: Database :: Front-Ends
License-File: LICENSE
